prime_test/__init__.py
prime_test/prime.py
prime_test-0.2.7.dist-info/LICENSE
prime_test-0.2.7.dist-info/METADATA
prime_test-0.2.7.dist-info/WHEEL
prime_test-0.2.7.dist-info/top_level.txt
prime_test-0.2.7.dist-info/RECORD
