Metadata-Version: 2.1
Name: prime-test
Version: 0.2.7
Summary: Checks if a number is prime
Author: Toby Connor-Kebbell
License: UNKNOWN
Platform: UNKNOWN
Classifier: Programming Language :: Python :: 3
Classifier: License :: OSI Approved :: MIT License
Classifier: Operating System :: OS Independent
License-File: LICENSE
